NEWGUNIA/__init__.py
NEWGUNIA/main.py
NewGunia-0.0.1.dist-info/License
NewGunia-0.0.1.dist-info/METADATA
NewGunia-0.0.1.dist-info/WHEEL
NewGunia-0.0.1.dist-info/top_level.txt
NewGunia-0.0.1.dist-info/RECORD
