Metadata-Version: 2.1
Name: NewGunia
Version: 0.0.1
Summary: New Gunia
Home-page: UNKNOWN
License: UNKNOWN
Platform: UNKNOWN
Classifier: Programming Language :: Python :: 3.8
Classifier: License :: OSI Approved :: MIT License
Requires-Python: >=3.6
License-File: License
